JsonhPy/JsonhPy.py
JsonhPy/__init__.py
jsonhpy-2.0.dist-info/licenses/LICENSE.md
jsonhpy-2.0.dist-info/METADATA
jsonhpy-2.0.dist-info/WHEEL
jsonhpy-2.0.dist-info/top_level.txt
jsonhpy-2.0.dist-info/RECORD
