Metadata-Version: 2.4
Name: JsonhPy
Version: 2.0
Summary: JSON for Humans in Python.
Author-email: Joyless <joyless.mod@gmail.com>
License-Expression: MIT
Project-URL: Homepage, https://github.com/jsonh-org/JsonhPy
Project-URL: Issues, https://github.com/jsonh-org/JsonhPy/issues
Classifier: Programming Language :: Python :: 3
Classifier: Operating System :: OS Independent
Requires-Python: >=3.12
License-File: LICENSE.md
Dynamic: license-file
